<?xml version="1.0" encoding="utf-8"?>
<DocTemplateDefinition xmlns:xsi="http://www.w3.org/2001/XMLSchema-instance" id="Swept_Solid_Geometry_3Zj3s_m9z8Ngphyp0n7JNE" Name="Swept Solid Geometry" UniqueId="e3b43dbe-c09f-485e-aceb-f330311d35ce" Type="IfcSweptAreaSolid">
	<Rules>
		<DocModelRuleAttribute Name="SweptArea" Identification="Profile">
			<Rules>
				<DocModelRuleEntity Name="IfcProfileDef" />
			</Rules>
		</DocModelRuleAttribute>
		<DocModelRuleAttribute Name="StyledByItem">
			<Rules>
				<DocModelRuleEntity Name="IfcStyledItem">
					<Rules>
						<DocModelRuleAttribute Name="Name">
							<Rules>
								<DocModelRuleEntity Name="IfcLabel" />
							</Rules>
						</DocModelRuleAttribute>
						<DocModelRuleAttribute Name="Styles">
							<Rules>
								<DocModelRuleEntity Name="IfcSurfaceStyle">
									<References>
										<DocTemplateDefinition xsi:nil="true" href="Surface_Color_Style_3gHpLYmULDnwrrpIILsus" />
									</References>
								</DocModelRuleEntity>
							</Rules>
						</DocModelRuleAttribute>
					</Rules>
				</DocModelRuleEntity>
			</Rules>
		</DocModelRuleAttribute>
	</Rules>
</DocTemplateDefinition>

