<?xml version="1.0" encoding="utf-8"?>
<DocTemplateDefinition xmlns:xsi="http://www.w3.org/2001/XMLSchema-instance" id="Extruded_Area_PolyCurve_Profile_0vGfUwztz11wdCdiiHT4tc" Name="Extruded Area PolyCurve Profile" UniqueId="394297ba-f77f-4107-a9cc-9ecb11744de6" Type="IfcExtrudedAreaSolid">
	<Rules>
		<DocModelRuleAttribute Name="Position">
			<Rules>
				<DocModelRuleEntity Name="IfcAxis2Placement3D">
					<Rules>
						<DocModelRuleAttribute Name="Location">
							<Rules>
								<DocModelRuleEntity Name="IfcCartesianPoint" />
							</Rules>
						</DocModelRuleAttribute>
						<DocModelRuleAttribute Name="Axis">
							<Rules>
								<DocModelRuleEntity Name="IfcDirection" />
							</Rules>
						</DocModelRuleAttribute>
						<DocModelRuleAttribute Name="RefDirection">
							<Rules>
								<DocModelRuleEntity Name="IfcDirection" />
							</Rules>
						</DocModelRuleAttribute>
					</Rules>
				</DocModelRuleEntity>
			</Rules>
		</DocModelRuleAttribute>
		<DocModelRuleAttribute Name="ExtrudedDirection">
			<Rules>
				<DocModelRuleEntity Name="IfcDirection" />
			</Rules>
		</DocModelRuleAttribute>
		<DocModelRuleAttribute Name="Depth">
			<Rules>
				<DocModelRuleEntity Name="IfcPositiveLengthMeasure" />
			</Rules>
		</DocModelRuleAttribute>
		<DocModelRuleAttribute Name="SweptArea" Identification="Profile">
			<Rules>
				<DocModelRuleEntity Name="IfcArbitraryClosedProfileDef">
					<References>
						<DocTemplateDefinition xsi:nil="true" href="PolyCurve_Profile_Definition_03SwXg4uT5lRy9kpp3a9BP" />
					</References>
				</DocModelRuleEntity>
				<DocModelRuleEntity Name="IfcArbitraryProfileDefWithVoids">
					<References>
						<DocTemplateDefinition xsi:nil="true" href="PolyCurve_with_Voids_Profile_Definition_3Jk6ORvbj0Twt7ndGj8PQH" />
					</References>
				</DocModelRuleEntity>
				<DocModelRuleEntity Name="IfcProfileDef" />
			</Rules>
		</DocModelRuleAttribute>
		<DocModelRuleAttribute Name="StyledByItem">
			<Rules>
				<DocModelRuleEntity Name="IfcStyledItem">
					<Rules>
						<DocModelRuleAttribute Name="Styles">
							<Rules>
								<DocModelRuleEntity Name="IfcSurfaceStyle" />
								<DocModelRuleEntity Name="IfcSurfaceStyle" />
								<DocModelRuleEntity Name="IfcSurfaceStyle" />
							</Rules>
						</DocModelRuleAttribute>
						<DocModelRuleAttribute Name="Name">
							<Rules>
								<DocModelRuleEntity Name="IfcLabel" />
								<DocModelRuleEntity Name="IfcLabel" />
								<DocModelRuleEntity Name="IfcLabel" />
							</Rules>
						</DocModelRuleAttribute>
					</Rules>
				</DocModelRuleEntity>
				<DocModelRuleEntity Name="IfcStyledItem" />
				<DocModelRuleEntity Name="IfcStyledItem" />
			</Rules>
		</DocModelRuleAttribute>
	</Rules>
</DocTemplateDefinition>

