<?xml version="1.0" encoding="utf-8"?>
<DocPropertyEnumeration xmlns:xsi="http://www.w3.org/2001/XMLSchema-instance" id="PEnum_InstalledCondition" Name="PEnum_InstalledCondition" UniqueId="d39e1dab-813f-4009-9449-e421e952085c">
	<Constants>
		<DocPropertyConstant xsi:nil="true" href="REGENERATED_17MDLQouz6lxmWikqT3W8p" />
		<DocPropertyConstant xsi:nil="true" href="REUSED_3XcFtPLQrEWebaiEfloayT" />
		<DocPropertyConstant xsi:nil="true" href="NEW_3mACAUuHT32vfUyn9RCZa2" />
		<DocPropertyConstant xsi:nil="true" href="OTHER_0SAtxxJj15wQA15w2MsIV" />
		<DocPropertyConstant xsi:nil="true" href="NOTKNOWN_0_n254Fb10hBW_0_XIj7Qe" />
		<DocPropertyConstant xsi:nil="true" href="UNSET_01y959UgrAlvv6_W__S9Ap" />
	</Constants>
</DocPropertyEnumeration>

