<?xml version="1.0" encoding="utf-8"?>
<DocPropertyEnumeration xmlns:xsi="http://www.w3.org/2001/XMLSchema-instance" id="PEnum_FiberColour" Name="PEnum_FiberColour" UniqueId="c9a60eb3-6d9c-422e-868a-4ec6150a8e4e">
	<Documentation>Enumeration of fiber colours.</Documentation>
	<Constants>
		<DocPropertyConstant xsi:nil="true" href="AQUA_34QSsKhPr71wPwhM1fnv4W" />
		<DocPropertyConstant xsi:nil="true" href="BLACK_2GrQ63mPvFPvvxcvRPl33O" />
		<DocPropertyConstant xsi:nil="true" href="BLUE_3S8sJRF7fB5BgAZ2SqovOL" />
		<DocPropertyConstant xsi:nil="true" href="BROWN_1BE__NruXFKfnT8__cCxpl" />
		<DocPropertyConstant xsi:nil="true" href="GREEN_0CfwzWTBb5W8z3woxY6g2z" />
		<DocPropertyConstant xsi:nil="true" href="ORANGE_0AsuIZzqr8pelfL8tC2R2X" />
		<DocPropertyConstant xsi:nil="true" href="RED_07j943yC14cxHOj4dqlmEq" />
		<DocPropertyConstant xsi:nil="true" href="ROSE_1Bdl0rVbz83vpzvMIBQcm4" />
		<DocPropertyConstant xsi:nil="true" href="SLATE_0Sg9IcEYDE9QlQk5hADvPj" />
		<DocPropertyConstant xsi:nil="true" href="VIOLET_33PSc8OSL65fy5KBD5pDMR" />
		<DocPropertyConstant xsi:nil="true" href="WHITE_2r1vye9T516vjv2XUxUInw" />
		<DocPropertyConstant xsi:nil="true" href="YELLOW_0h4JumSAH0yPibYW0AqHap" />
		<DocPropertyConstant xsi:nil="true" href="OTHER_0SAtxxJj15wQA15w2MsIV" />
		<DocPropertyConstant xsi:nil="true" href="NOTKNOWN_0_n254Fb10hBW_0_XIj7Qe" />
		<DocPropertyConstant xsi:nil="true" href="UNSET_01y959UgrAlvv6_W__S9Ap" />
	</Constants>
</DocPropertyEnumeration>

