<?xml version="1.0" encoding="utf-8"?>
<DocChangeSet xmlns:xsi="http://www.w3.org/2001/XMLSchema-instance" Name="IFC4x3_RC2 Update" UniqueId="486d3ac0-77c9-41bc-a4e5-57b4114f567d" VersionBaseline="4.3.0.0">
	<ChangesEntities>
		<DocChangeAction Name="Shared element data schemas" UniqueId="ebe7ced7-14fe-4936-ab33-2d4870a9492d">
			<Changes>
				<DocChangeAction Name="IfcSharedInfrastructureElements" UniqueId="19e131cd-3e04-4d8d-bddd-0dd896583c8d">
					<Changes>
						<DocChangeAction Name="IfcSpatialReferenceSelect" UniqueId="2407f1a3-bb9c-48d8-9b15-03d55ef1d350">
							<Changes>
								<DocChangeAction Name="IfcGroup" UniqueId="ae3ed89e-591e-4206-9ba2-8b60f458c211" Action="added" />
								<DocChangeAction Name="IfcSystem" UniqueId="ea4bf34b-4ce0-4837-b78e-40c9c6ca54a3" Action="deleted" />
							</Changes>
						</DocChangeAction>
					</Changes>
				</DocChangeAction>
			</Changes>
		</DocChangeAction>
		<DocChangeAction Name="Resource definition data schemas" UniqueId="1f9f4242-6ea4-463c-85a5-fecb47ad250c">
			<Changes>
				<DocChangeAction Name="IfcGeometricConstraintResource" UniqueId="a3f5caab-37e0-44ca-b666-5a9fdfa1d410">
					<Changes>
						<DocChangeAction Name="IfcAlignmentHorizontalSegmentTypeEnum" UniqueId="f474bf33-1f26-4964-89a5-b223d0cd20eb">
							<Changes>
								<DocChangeAction Name="CUBICPARABOLA" UniqueId="dcf59c42-5d0e-4a8c-afd9-26de3b750c13" Action="added" />
							</Changes>
						</DocChangeAction>
					</Changes>
				</DocChangeAction>
				<DocChangeAction Name="IfcGeometryResource" UniqueId="5d194a2f-c528-44d5-9121-b2ed4e9f97f8">
					<Changes>
						<DocChangeAction Name="IfcCurveSegment" UniqueId="fb4baae8-0dc4-475e-9686-d98437d96569">
							<Changes>
								<DocChangeAction Name="Placement" UniqueId="8a4920c6-7245-4b4c-9a22-947d2f62f883" Action="modified" ImpactXML="true">
									<Aspects>
										<DocChangeAspect Aspect="name" OldValue="StartPlacement" NewValue="Placement" />
									</Aspects>
								</DocChangeAction>
								<DocChangeAction Name="SegmentStart" UniqueId="ac8d84f9-a07f-4567-95d4-af6431628557" Action="modified" ImpactXML="true">
									<Aspects>
										<DocChangeAspect Aspect="name" OldValue="SegmentLength" NewValue="SegmentStart" />
									</Aspects>
								</DocChangeAction>
								<DocChangeAction Name="SegmentLength" UniqueId="03f9b4b6-6c11-4606-b9de-a3b817671eea" Action="modified" ImpactSPF="true" ImpactXML="true">
									<Aspects>
										<DocChangeAspect Aspect="name" OldValue="ParentCurve" NewValue="SegmentLength" />
										<DocChangeAspect Aspect="type" OldValue="IfcCurve" NewValue="IfcCurveMeasureSelect" />
									</Aspects>
								</DocChangeAction>
								<DocChangeAction Name="ParentCurve" UniqueId="394a58a0-ae65-45b4-bcb1-12e0bd69f07f" Action="added" />
							</Changes>
						</DocChangeAction>
					</Changes>
				</DocChangeAction>
			</Changes>
		</DocChangeAction>
	</ChangesEntities>
	<ChangesProperties>
		<DocChangeAction Name="PEnum_RiskRating" UniqueId="62c195c4-dc85-428a-b43c-483b69c46436">
			<Changes>
				<DocChangeAction Name="CRITICAL" UniqueId="401ce9d2-5254-46d6-abfb-3bc21e699f42" Action="added" />
				<DocChangeAction Name="CONSIDERABLE" UniqueId="67ac6746-08db-4fed-bd86-2219c9599575" Action="added" />
				<DocChangeAction Name="SOME" UniqueId="beb19f6b-a423-41b4-a438-ade72231319b" Action="added" />
				<DocChangeAction Name="INSIGNIFICANT" UniqueId="4fe69b1c-5848-4d01-b30e-298743eb01c9" Action="added" />
				<DocChangeAction Name="UNSET" UniqueId="6be5f615-75da-4de6-9110-bcd887478a45" Action="added" />
				<DocChangeAction Name="NOTAPPLICABLE" UniqueId="a5666946-b973-47c9-8c8c-6070a4e902d8" Action="deleted" />
			</Changes>
		</DocChangeAction>
	</ChangesProperties>
</DocChangeSet>

